verx/__init__.py
verx/_modidx.py
verx/cons.py
verx/util.py
verx/verx.py
verx-0.0.1.dist-info/LICENSE
verx-0.0.1.dist-info/METADATA
verx-0.0.1.dist-info/WHEEL
verx-0.0.1.dist-info/entry_points.txt
verx-0.0.1.dist-info/top_level.txt
verx-0.0.1.dist-info/RECORD
