Metadata-Version: 2.1
Name: verx
Version: 0.0.1
Summary: version extra version ver verx
Home-page: https://github.com/dsm-72/verx
Author: dsm-72
Author-email: sumner.magruder@yale.edu
License: Apache Software License 2.0
Classifier: Development Status :: 4 - Beta
Classifier: Intended Audience :: Developers
Classifier: Natural Language :: English
Classifier: Programming Language :: Python :: 3.11
Classifier: License :: OSI Approved :: Apache Software License
Requires-Python: >=3.11
License-File: LICENSE
Requires-Dist: nlit
Requires-Dist: atyp
Requires-Dist: chck
Requires-Dist: nchr
Provides-Extra: dev
